README.rst
setup.py
drf_url_content_type_override/__init__.py
drf_url_content_type_override.egg-info/PKG-INFO
drf_url_content_type_override.egg-info/SOURCES.txt
drf_url_content_type_override.egg-info/dependency_links.txt
drf_url_content_type_override.egg-info/not-zip-safe
drf_url_content_type_override.egg-info/requires.txt
drf_url_content_type_override.egg-info/top_level.txt
tests/__init__.py
tests/settings.py
tests/test_content_type.py