Metadata-Version: 1.1
Name: drf-url-content-type-override
Version: 1.0.0
Summary: The name says it all.
Home-page: UNKNOWN
Author: Chris McKenzie
Author-email: me@christophermckenzie.com
License: LICENSE.txt
Platform: UNKNOWN
Classifier: Environment :: Web Environment
Classifier: Framework :: Django
Classifier: Intended Audience :: Developers
Classifier: Operating System :: OS Independent
Classifier: Programming Language :: Python
Classifier: Topic :: Internet :: WWW/HTTP
